example/__init__.py
example/app.py
example/app_test.py
example/static/favicon.ico
example/templates/example.html
example/templates/index.html
example/templates/gourde/base.html
gourde/__init__.py
gourde/gourde.py
gourde/gourde_test.py
gourde/testutils.py
gourde/templates/gourde/_base.html
gourde/templates/gourde/base.html
gourde/templates/gourde/status.html
gourde/templates/gourde/threads.html
gourde-0.2.1.dist-info/DESCRIPTION.rst
gourde-0.2.1.dist-info/METADATA
gourde-0.2.1.dist-info/RECORD
gourde-0.2.1.dist-info/WHEEL
gourde-0.2.1.dist-info/entry_points.txt
gourde-0.2.1.dist-info/metadata.json
gourde-0.2.1.dist-info/top_level.txt
