Metadata-Version: 2.0
Name: gourde
Version: 0.2.1
Summary: Flask(-Twisted) microframework for microservices with Prometheus and Sentry support.
Home-page: https://github.com/criteo/gourde/
Author: Corentin Chary
Author-email: c.chary@criteo.com
License: Apache 2
Project-URL: Source Code, https://github.com/criteo/gourde/
Keywords: flask twisted microframework microservice prometheus sentry
Platform: UNKNOWN
Classifier: Environment :: Web Environment
Classifier: Intended Audience :: Developers
Classifier: Intended Audience :: System Administrators
Classifier: License :: OSI Approved :: Apache Software License
Classifier: Programming Language :: Python :: 2.7
Classifier: Programming Language :: Python :: 3.5
Classifier: Programming Language :: Python :: 3.6
Classifier: Programming Language :: Python :: 3.7
Requires-Dist: Flask
Requires-Dist: prometheus-client
Requires-Dist: prometheus-flask-exporter
Requires-Dist: blinker
Requires-Dist: raven
Requires-Dist: flask-twisted
Requires-Dist: twisted
